{
  "milestone": 407,
  "date": "2026-05-04",
  "summary": "M407 — combat grid mobile fix (followup to M406). Reverted the .ev-battlefield top:90px CSS hack which had desynced the SVG tile layer from the canvas character layer. Now both layers share the same mobile-aware sky percentage (0.42 in EvBattlefield, 0.40 in CombatScreen canvas) so tiles and characters move together. Added clamps so back-row sprite heads can't exit the viewport top and front-row tiles can't exceed the element height.",
  "categories": [
    "feature"
  ],
  "breakingChanges": []
}